pydabax/__init__.py
pydabax/dabax.py
pydabax/elements.py
pydabax/skeleton.py
pydabax/data/xraydb.latest.json
pyDABAX-0.3.1.dist-info/AUTHORS.rst
pyDABAX-0.3.1.dist-info/LICENSE.txt
pyDABAX-0.3.1.dist-info/METADATA
pyDABAX-0.3.1.dist-info/WHEEL
pyDABAX-0.3.1.dist-info/top_level.txt
pyDABAX-0.3.1.dist-info/RECORD
