Metadata-Version: 2.1
Name: pyDABAX
Version: 0.3.1
Summary: Fast x-ray and neutron database
Home-page: https://github.com/JulianMars
Author: Julian Mars
Author-email: jmars@mailbox.org
License: mit
Project-URL: Documentation, https://github.com/JulianMars/pyDABAX
Platform: any
Classifier: Development Status :: 4 - Beta
Classifier: Programming Language :: Python
License-File: LICENSE.txt
License-File: AUTHORS.rst
Requires-Dist: importlib-metadata
Requires-Dist: pandas
Requires-Dist: tinydb (>=4.7.0)
Requires-Dist: numpy (>=1.23)
Requires-Dist: astropy (>=5.0)
Requires-Dist: regex
Provides-Extra: testing
Requires-Dist: pytest ; extra == 'testing'
Requires-Dist: pytest-cov ; extra == 'testing'
